.gitignore
CHANGES.txt
CONTRIBUTORS.txt
MANIFEST.in
README.rst
TODO.txt
bootstrap.py
buildout.cfg
setup.cfg
setup.py
docs/LICENSE.GPL
docs/LICENSE.txt
src/collective/__init__.py
src/collective.pageheader.egg-info/PKG-INFO
src/collective.pageheader.egg-info/SOURCES.txt
src/collective.pageheader.egg-info/dependency_links.txt
src/collective.pageheader.egg-info/entry_points.txt
src/collective.pageheader.egg-info/namespace_packages.txt
src/collective.pageheader.egg-info/not-zip-safe
src/collective.pageheader.egg-info/requires.txt
src/collective.pageheader.egg-info/top_level.txt
src/collective/pageheader/__init__.py
src/collective/pageheader/configure.zcml
src/collective/pageheader/extenders.py
src/collective/pageheader/interfaces.py
src/collective/pageheader/testing.py
src/collective/pageheader/utils.py
src/collective/pageheader/browser/__init__.py
src/collective/pageheader/browser/configure.zcml
src/collective/pageheader/browser/viewlet_pageheader.pt
src/collective/pageheader/browser/viewlets.py
src/collective/pageheader/browser/views.py
src/collective/pageheader/browser/resources/styles.css
src/collective/pageheader/locales/collective.pageheader.pot
src/collective/pageheader/locales/rebuild_i18n.sh
src/collective/pageheader/locales/en/LC_MESSAGES/collective.pageheader.po
src/collective/pageheader/locales/it/LC_MESSAGES/collective.pageheader.po
src/collective/pageheader/profiles/default/actions.xml
src/collective/pageheader/profiles/default/browserlayer.xml
src/collective/pageheader/profiles/default/metadata.xml
src/collective/pageheader/tests/__init__.py
src/collective/pageheader/tests/robot_test.txt
src/collective/pageheader/tests/test_example.py
src/collective/pageheader/tests/test_robot.py