Metadata-Version: 1.0
Name: collective.pageheader
Version: 1.0.1
Summary: UNKNOWN
Home-page: https://github.com/simahawk/collective.pageheader
Author: Simone Orsi [simahawk]
Author-email: simahawk@gmail.com
License: gpl
Platform: UNKNOWN
Classifier: Environment :: Web Environment
Classifier: Framework :: Plone
Classifier: Operating System :: OS Independent
Classifier: Programming Language :: Python
Classifier: Programming Language :: Python :: 2.6
Classifier: Topic :: Software Development :: Libraries :: Python Modules
